dspeed/__init__.py
dspeed/_version.py
dspeed/build_dsp.py
dspeed/cli.py
dspeed/errors.py
dspeed/logging.py
dspeed/processing_chain.py
dspeed/units.py
dspeed/utils.py
dspeed/processors/__init__.py
dspeed/processors/arithmetic.py
dspeed/processors/bl_subtract.py
dspeed/processors/convolutions.py
dspeed/processors/dwt.py
dspeed/processors/energy_kernels.py
dspeed/processors/fft.py
dspeed/processors/fixed_time_pickoff.py
dspeed/processors/gaussian_filter1d.py
dspeed/processors/get_multi_local_extrema.py
dspeed/processors/get_wf_centroid.py
dspeed/processors/histogram.py
dspeed/processors/histogram_stats.py
dspeed/processors/iir_filter.py
dspeed/processors/inject_ringing.py
dspeed/processors/inl_correction.py
dspeed/processors/kernels.py
dspeed/processors/linear_slope_fit.py
dspeed/processors/log_check.py
dspeed/processors/min_max.py
dspeed/processors/ml.py
dspeed/processors/moving_windows.py
dspeed/processors/multi_a_filter.py
dspeed/processors/multi_t_filter.py
dspeed/processors/nnls.py
dspeed/processors/optimize.py
dspeed/processors/param_lookup.py
dspeed/processors/peak_snr_threshold.py
dspeed/processors/pmt_pulse_injector.py
dspeed/processors/pole_zero.py
dspeed/processors/poly_fit.py
dspeed/processors/presum.py
dspeed/processors/pulse_injector.py
dspeed/processors/rc_cr2.py
dspeed/processors/recursive_filter.py
dspeed/processors/round_to_nearest.py
dspeed/processors/saturation.py
dspeed/processors/soft_pileup_corr.py
dspeed/processors/sort.py
dspeed/processors/svm.py
dspeed/processors/tf_model.py
dspeed/processors/time_over_threshold.py
dspeed/processors/time_point_thresh.py
dspeed/processors/trap_filters.py
dspeed/processors/unit_conversion.py
dspeed/processors/upsampler.py
dspeed/processors/wf_alignment.py
dspeed/processors/wf_correction.py
dspeed/processors/where.py
dspeed/processors/wiener_filter.py
dspeed/processors/windower.py
dspeed/vis/__init__.py
dspeed/vis/waveform_browser.py
dspeed-2.1.1.dist-info/licenses/LICENSE
dspeed-2.1.1.dist-info/METADATA
dspeed-2.1.1.dist-info/WHEEL
dspeed-2.1.1.dist-info/entry_points.txt
dspeed-2.1.1.dist-info/top_level.txt
dspeed-2.1.1.dist-info/RECORD
