Metadata-Version: 2.4
Name: dspeed
Version: 2.1.1
Summary: Fast Digital Signal Processing for particle detectors in Python
Author-email: Ian Guinn <guinnis@ornl.gov>
Maintainer: The LEGEND collaboration
Project-URL: Homepage, https://github.com/legend-exp/dspeed
Project-URL: Bug Tracker, https://github.com/legend-exp/dspeed/issues
Project-URL: Discussions, https://github.com/legend-exp/dspeed/discussions
Project-URL: Changelog, https://github.com/legend-exp/dspeed/releases
Classifier: Development Status :: 4 - Beta
Classifier: Intended Audience :: Developers
Classifier: Intended Audience :: Information Technology
Classifier: Intended Audience :: Science/Research
Classifier: License :: OSI Approved :: GNU General Public License v3 (GPLv3)
Classifier: Operating System :: MacOS
Classifier: Operating System :: POSIX
Classifier: Operating System :: Unix
Classifier: Programming Language :: Python
Classifier: Programming Language :: Python :: 3
Classifier: Programming Language :: Python :: 3 :: Only
Classifier: Topic :: Scientific/Engineering
Classifier: Topic :: Scientific/Engineering :: Information Analysis
Classifier: Topic :: Scientific/Engineering :: Mathematics
Classifier: Topic :: Scientific/Engineering :: Physics
Classifier: Topic :: Software Development
Requires-Python: >=3.10
License-File: LICENSE
Requires-Dist: PyWavelets
Requires-Dist: colorlog
Requires-Dist: dbetto
Requires-Dist: h5py>=3.2
Requires-Dist: iminuit
Requires-Dist: legend-pydataobj>=1.16.0
Requires-Dist: matplotlib
Requires-Dist: numba!=0.53.*,!=0.54.*
Requires-Dist: numpy>2
Requires-Dist: parse
Requires-Dist: pint
Requires-Dist: pyarrow
Requires-Dist: pyyaml
Requires-Dist: scipy
Requires-Dist: tqdm>=4.27
Provides-Extra: all
Requires-Dist: dspeed[docs,test]; extra == "all"
Provides-Extra: docs
Requires-Dist: furo; extra == "docs"
Requires-Dist: jupyter; extra == "docs"
Requires-Dist: myst-parser; extra == "docs"
Requires-Dist: nbsphinx; extra == "docs"
Requires-Dist: sphinx; extra == "docs"
Requires-Dist: sphinx-copybutton; extra == "docs"
Requires-Dist: sphinx-inline-tabs; extra == "docs"
Provides-Extra: test
Requires-Dist: pre-commit; extra == "test"
Requires-Dist: pylegendtestdata; extra == "test"
Requires-Dist: pytest>=6.0; extra == "test"
Requires-Dist: pytest-cov; extra == "test"
Dynamic: license-file
